{
        "core" : [
            {
                "type": "Tool Links",
                "components" : [
                    {
                        "id": "jenkins",
                        "title": "jenkins",
                        "img": "img/jenkins.png",
                        "description": "Continuous Integration & Automation Server",
                        "link": "",
                        "linkCreate": {
                            "host": "jenkins",
							"endPath": ""
                        }
                    },
                    {
                        "id": "gitlab",
                        "title": "gitlab",
                        "img": "img/gitlab.svg",
                        "description": "Git Repository Management & Code Review Tool",
                        "link": "",
                        "linkCreate": {
                            "host": "gitlab-ce",
							"endPath": ""
                        }
                    },
                    {
                        "id": "sonar",
                        "title": "sonar",
                        "img": "img/sonar.png",
                        "description": "Static Code Analysis",
                        "link": "",
                        "linkCreate": {
                            "host": "sonar",
							"endPath": ""
                        }
                    },
                    {
                        "id": "nexus",
                        "title": "nexus",
                        "img": "img/nexus.png",
                        "description": "Software Repository Manager",
                        "link": "",
                        "linkCreate": {
                            "host": "nexus",
							"endPath": ""
                        }
                    },
                    {
 
                       "id": "kibana",
                        "title": "kibana",
                        "img": "img/kibana.png",
                        "description": "Kibana Dashboard for Logging (ELK)",
                        "link": "",
                        "linkCreate": {
                            "host": "kibana",
							"endPath": "/app/kibana"
                        }
                    },
                    {
                        "id": "selenium",
                        "title": "selenium",
                        "img": "img/selenium.png",
                        "description": "Selenium Grid for Automated Testing",
                        "link": "",
                        "linkCreate": {
                            "host": "selenium",
                            "endPath": "/grid/console"
                        }
                    },
                    {
                        "id": "prometheus",
                        "title": "prometheus",
                        "img": "img/prometheus.png",
                        "description": "Prometheus Monitoring Stack",
                        "link": "",
                        "linkCreate": {
                            "host": "prometheus",
							"endPath": ""
                        }
                    },
                    {
                        "id": "ldap-ltb",
                        "title": "ltb",
                        "img": "img/ltb.png",
                        "description": "Application that allows users to change their password in an LDAP directory",
                        "link": "",
                        "linkCreate": {
                            "host": "adop-ldap-ltb",
							"endPath": ""
                        }
                    },
                    {
                        "id": "ldap-phpadmin",
                        "title": "phpldapadmin",
                        "img": "img/phpldapadmin.png",
                        "description": "Browser to manage your LDAP server",
                        "link": "",
                        "linkCreate": {
                            "host": "adop-ldap-phpadmin",
							"endPath": ""
                        }
                    }
                ]
            }
        ],
        "blueprints": [
            {"url": "bp/demo-release-note.html"}
        ]
    }